aarchimate.py
aarchimate-1.0.0.dist-info/DESCRIPTION.rst
aarchimate-1.0.0.dist-info/METADATA
aarchimate-1.0.0.dist-info/RECORD
aarchimate-1.0.0.dist-info/WHEEL
aarchimate-1.0.0.dist-info/metadata.json
aarchimate-1.0.0.dist-info/top_level.txt
