Metadata-Version: 2.0
Name: aarchimate
Version: 1.0.0
Summary: Aarchimate
Home-page: https://github.com/thomwiggers/aarchimate
Author: Thom Wiggers
Author-email: thom@thomwiggers.nl
License: BSD
Keywords: arm64 aarch64 assembly compilers
Platform: UNKNOWN
Classifier: Development Status :: 3 - Alpha
Classifier: Intended Audience :: Developers
Classifier: Topic :: Software Development :: Build Tools
Classifier: License :: OSI Approved :: BSD License
Classifier: Programming Language :: Python :: 3.6
